[
  {
    "video_id": "mQAEdV39CLo",
    "url": "https://www.youtube.com/watch?v=mQAEdV39CLo",
    "title": "Buscaba responde y encontró el infierno",
    "channel": "ONE Media Español",
    "channel_id": "UCcVNDl7ZJMf9lC9a34CY4RA",
    "published": "2026-01-26T14:40:59Z",
    "found_at": "2026-01-27T03:02:54.646262",
    "status": "metadata_update",
    "sanitized_name": "Buscaba responde y encontró el infierno"
  },
  {
    "video_id": "TOKgZeeN34E",
    "url": "https://www.youtube.com/watch?v=TOKgZeeN34E",
    "title": "EL MAGO DEL KREMLIN Tráiler Español (2026) Jude Law",
    "channel": "ONE Media Español",
    "channel_id": "UCcVNDl7ZJMf9lC9a34CY4RA",
    "published": "2026-01-26T10:57:37Z",
    "found_at": "2026-01-26T14:16:31.414886",
    "status": "pending",
    "sanitized_name": "EL MAGO DEL KREMLIN Tráiler Español (2026) Jude Law"
  },
  {
    "video_id": "TKez4hpZkJQ",
    "url": "https://www.youtube.com/watch?v=TKez4hpZkJQ",
    "title": "&quot;Yoshi come&quot; SUPER MARIO GALAXY: La Película Tráiler 2 Español Latino (2026)",
    "channel": "ONE Media Español",
    "channel_id": "UCcVNDl7ZJMf9lC9a34CY4RA",
    "published": "2026-01-25T22:59:12Z",
    "found_at": "2026-01-26T14:16:31.414904",
    "status": "pending",
    "sanitized_name": "&quot;Yoshi come&quot; SUPER MARIO GALAXY_ La Película Tráiler 2 Español Latino (2026)"
  },
  {
    "video_id": "ghsa-1eo8jk",
    "url": "https://www.youtube.com/watch?v=ghsa-1eo8jk",
    "title": "EVOLUTION Todos Los Tráilers Español (2026)",
    "channel": "ONE Media Español",
    "channel_id": "UCcVNDl7ZJMf9lC9a34CY4RA",
    "published": "2026-01-25T15:30:23Z",
    "found_at": "2026-01-26T14:16:31.414908",
    "status": "pending",
    "sanitized_name": "EVOLUTION Todos Los Tráilers Español (2026)"
  },
  {
    "video_id": "x1JuQD6EIO8",
    "url": "https://www.youtube.com/watch?v=x1JuQD6EIO8",
    "title": "SUPER MARIO GALAXY: La Película Tráiler 2 Español (2026) Yoshi",
    "channel": "ONE Media Español",
    "channel_id": "UCcVNDl7ZJMf9lC9a34CY4RA",
    "published": "2026-01-25T15:16:45Z",
    "found_at": "2026-01-26T14:16:31.414910",
    "status": "pending",
    "sanitized_name": "SUPER MARIO GALAXY_ La Película Tráiler 2 Español (2026) Yoshi"
  },
  {
    "video_id": "L5VGFQHyeL4",
    "url": "https://www.youtube.com/watch?v=L5VGFQHyeL4",
    "title": "SUPER MARIO GALAXY: La Película Tráiler 2 Español Latino (2026) Yoshi",
    "channel": "ONE Media Español",
    "channel_id": "UCcVNDl7ZJMf9lC9a34CY4RA",
    "published": "2026-01-25T14:23:58Z",
    "found_at": "2026-01-26T14:16:31.414913",
    "status": "pending",
    "sanitized_name": "SUPER MARIO GALAXY_ La Película Tráiler 2 Español Latino (2026) Yoshi"
  },
  {
    "video_id": "0YoqxaZC1Ns",
    "url": "https://www.youtube.com/watch?v=0YoqxaZC1Ns",
    "title": "LAS MEJORES PELÍCULAS PRÓXIMAS DE 2026 Tráilers",
    "channel": "ONE Media Español",
    "channel_id": "UCcVNDl7ZJMf9lC9a34CY4RA",
    "published": "2026-01-23T19:00:01Z",
    "found_at": "2026-01-26T14:16:31.414915",
    "status": "pending",
    "sanitized_name": "LAS MEJORES PELÍCULAS PRÓXIMAS DE 2026 Tráilers"
  },
  {
    "video_id": "Vbxf-jdzDX8",
    "url": "https://www.youtube.com/watch?v=Vbxf-jdzDX8",
    "title": "SUPERGIRL &quot;Lobo&quot; Tráiler Español Latino (2026) Jason Momoa",
    "channel": "ONE Media Español",
    "channel_id": "UCcVNDl7ZJMf9lC9a34CY4RA",
    "published": "2026-01-23T17:40:17Z",
    "found_at": "2026-01-26T14:16:31.414917",
    "status": "pending",
    "sanitized_name": "SUPERGIRL &quot;Lobo&quot; Tráiler Español Latino (2026) Jason Momoa"
  },
  {
    "video_id": "AMp0dl9L6jI",
    "url": "https://www.youtube.com/watch?v=AMp0dl9L6jI",
    "title": "LA MUERTE DE ROBIN HOOD Tráiler Español Latino (2026) Hugh Jackman",
    "channel": "ONE Media Español",
    "channel_id": "UCcVNDl7ZJMf9lC9a34CY4RA",
    "published": "2026-01-23T17:22:18Z",
    "found_at": "2026-01-26T14:16:31.414919",
    "status": "pending",
    "sanitized_name": "LA MUERTE DE ROBIN HOOD Tráiler Español Latino (2026) Hugh Jackman"
  },
  {
    "video_id": "jGYYIKFgYmU",
    "url": "https://www.youtube.com/watch?v=jGYYIKFgYmU",
    "title": "AMOS DEL UNIVERSO Tráiler Español Latino (2026)",
    "channel": "ONE Media Español",
    "channel_id": "UCcVNDl7ZJMf9lC9a34CY4RA",
    "published": "2026-01-23T16:03:58Z",
    "found_at": "2026-01-26T14:16:31.414922",
    "status": "pending",
    "sanitized_name": "AMOS DEL UNIVERSO Tráiler Español Latino (2026)"
  },
  {
    "video_id": "xjFjKRwWMtM",
    "url": "https://www.youtube.com/watch?v=xjFjKRwWMtM",
    "title": "LOVE ME LOVE ME Tráiler Español (2026)",
    "channel": "ONE Media Español",
    "channel_id": "UCcVNDl7ZJMf9lC9a34CY4RA",
    "published": "2026-01-23T14:49:34Z",
    "found_at": "2026-01-26T14:16:31.414926",
    "status": "pending",
    "sanitized_name": "LOVE ME LOVE ME Tráiler Español (2026)"
  },
  {
    "video_id": "Rqwfh2fg2rs",
    "url": "https://www.youtube.com/watch?v=Rqwfh2fg2rs",
    "title": "STAR WARS: MAUL Señor de las sombras Tráiler Español (2026)",
    "channel": "ONE Media Español",
    "channel_id": "UCcVNDl7ZJMf9lC9a34CY4RA",
    "published": "2026-01-22T17:59:30Z",
    "found_at": "2026-01-26T14:16:31.414928",
    "status": "pending",
    "sanitized_name": "STAR WARS_ MAUL Señor de las sombras Tráiler Español (2026)"
  },
  {
    "video_id": "eVCdT_Y6tx0",
    "url": "https://www.youtube.com/watch?v=eVCdT_Y6tx0",
    "title": "STAR WARS: MAUL Lord de las Sombras Tráiler Español Latino Doblado (2026)",
    "channel": "ONE Media Español",
    "channel_id": "UCcVNDl7ZJMf9lC9a34CY4RA",
    "published": "2026-01-22T17:52:12Z",
    "found_at": "2026-01-26T14:16:31.414930",
    "status": "pending",
    "sanitized_name": "STAR WARS_ MAUL Lord de las Sombras Tráiler Español Latino Doblado (2026)"
  },
  {
    "video_id": "IlA7Kyx2Szk",
    "url": "https://www.youtube.com/watch?v=IlA7Kyx2Szk",
    "title": "INVENCIBLE Temporada 4 Tráiler Español (2026)",
    "channel": "ONE Media Español",
    "channel_id": "UCcVNDl7ZJMf9lC9a34CY4RA",
    "published": "2026-01-22T17:21:35Z",
    "found_at": "2026-01-26T14:16:31.414934",
    "status": "pending",
    "sanitized_name": "INVENCIBLE Temporada 4 Tráiler Español (2026)"
  },
  {
    "video_id": "GHs5tzHyHhs",
    "url": "https://www.youtube.com/watch?v=GHs5tzHyHhs",
    "title": "INVENCIBLE Temporada 4 Tráiler Español Latino (2026)",
    "channel": "ONE Media Español",
    "channel_id": "UCcVNDl7ZJMf9lC9a34CY4RA",
    "published": "2026-01-22T17:11:33Z",
    "found_at": "2026-01-26T14:16:31.414937",
    "status": "pending",
    "sanitized_name": "INVENCIBLE Temporada 4 Tráiler Español Latino (2026)"
  },
  {
    "video_id": "eyeYFhrRAXI",
    "url": "https://www.youtube.com/watch?v=eyeYFhrRAXI",
    "title": "RETURN TO SILENT HILL Todos Los Clipes y Tráilers Español (2026)",
    "channel": "ONE Media Español",
    "channel_id": "UCcVNDl7ZJMf9lC9a34CY4RA",
    "published": "2026-01-22T14:30:38Z",
    "found_at": "2026-01-26T14:16:31.414939",
    "status": "pending",
    "sanitized_name": "RETURN TO SILENT HILL Todos Los Clipes y Tráilers Español (2026)"
  },
  {
    "video_id": "Nx6QeEWpsb4",
    "url": "https://www.youtube.com/watch?v=Nx6QeEWpsb4",
    "title": "SEND HELP Tráiler 2 Español (2026) Dylan O&#39;Brien, Rachel McAdams",
    "channel": "ONE Media Español",
    "channel_id": "UCcVNDl7ZJMf9lC9a34CY4RA",
    "published": "2026-01-22T11:42:45Z",
    "found_at": "2026-01-27T03:02:54.646282",
    "status": "metadata_update",
    "sanitized_name": "SEND HELP Tráiler 2 Español (2026) Dylan O&#39;Brien, Rachel McAdams"
  },
  {
    "video_id": "1kokgE5cw3c",
    "url": "https://www.youtube.com/watch?v=1kokgE5cw3c",
    "title": "56 DÍAS Tráiler Español Latino (2026) Dove Cameron",
    "channel": "ONE Media Español",
    "channel_id": "UCcVNDl7ZJMf9lC9a34CY4RA",
    "published": "2026-01-21T15:40:54Z",
    "found_at": "2026-01-26T14:16:31.414941",
    "status": "pending",
    "sanitized_name": "56 DÍAS Tráiler Español Latino (2026) Dove Cameron"
  },
  {
    "video_id": "UboYpOPFggU",
    "url": "https://www.youtube.com/watch?v=UboYpOPFggU",
    "title": "EL ÚLTIMO VIKINGO Tráiler Español (2026) Mads Mikkelsen",
    "channel": "ONE Media Español",
    "channel_id": "UCcVNDl7ZJMf9lC9a34CY4RA",
    "published": "2026-01-21T14:25:41Z",
    "found_at": "2026-01-26T14:16:31.414945",
    "status": "pending",
    "sanitized_name": "EL ÚLTIMO VIKINGO Tráiler Español (2026) Mads Mikkelsen"
  },
  {
    "video_id": "xA3P1IXkaQs",
    "url": "https://www.youtube.com/watch?v=xA3P1IXkaQs",
    "title": "LÍBRALOS DEL MAL Tráiler 2 Español Latino (2026) Terror",
    "channel": "ONE Media Español",
    "channel_id": "UCcVNDl7ZJMf9lC9a34CY4RA",
    "published": "2026-01-21T13:23:56Z",
    "found_at": "2026-01-26T14:16:31.414947",
    "status": "pending",
    "sanitized_name": "LÍBRALOS DEL MAL Tráiler 2 Español Latino (2026) Terror"
  },
  {
    "video_id": "MB50R72fSyE",
    "url": "https://www.youtube.com/watch?v=MB50R72fSyE",
    "title": "El arte de Sarah | Tráiler oficial | Netflix",
    "channel": "Netflix Latinoamérica",
    "channel_id": "UC5ZiUaIJ2b5dYBYGf5iEUrA",
    "published": "2026-01-27T00:00:01Z",
    "found_at": "2026-01-27T03:02:55.136194",
    "status": "uploaded",
    "sanitized_name": "El arte de Sarah _ Tráiler oficial _ Netflix",
    "metadata_updated_at": "2026-01-27T03:06:35.280707",
    "uploaded_at": "2026-01-27T03:06:40.927259",
    "youtube_id": "xzt4DpLECEA"
  },
  {
    "video_id": "K0LBMMrTJZ8",
    "url": "https://www.youtube.com/watch?v=K0LBMMrTJZ8",
    "title": "Bridgerton: Temporada 4 | Conoce a Sophie Baek | Netflix",
    "channel": "Netflix Latinoamérica",
    "channel_id": "UC5ZiUaIJ2b5dYBYGf5iEUrA",
    "published": "2026-01-23T14:00:00Z",
    "found_at": "2026-01-26T14:16:31.651087",
    "status": "uploaded",
    "sanitized_name": "Bridgerton_ Temporada 4 _ Conoce a Sophie Baek _ Netflix",
    "metadata_updated_at": "2026-01-26T14:19:51.681956",
    "uploaded_at": "2026-01-26T14:19:59.339166",
    "youtube_id": "DjBsnRzBFG4"
  },
  {
    "video_id": "jsJG8BD6NFQ",
    "url": "https://www.youtube.com/watch?v=jsJG8BD6NFQ",
    "title": "¿Cómo se traduce este amor? | Detrás de cámaras: Vol.1 - Japón y Canadá | Netflix",
    "channel": "Netflix Latinoamérica",
    "channel_id": "UC5ZiUaIJ2b5dYBYGf5iEUrA",
    "published": "2026-01-23T09:00:00Z",
    "found_at": "2026-01-26T14:16:31.651102",
    "status": "pending",
    "sanitized_name": "¿Cómo se traduce este amor_ _ Detrás de cámaras_ Vol.1 - Japón y Canadá _ Netflix"
  },
  {
    "video_id": "gFkJCe-m6tQ",
    "url": "https://www.youtube.com/watch?v=gFkJCe-m6tQ",
    "title": "El 2026 tiene algo para todos | ¿Qué sigue? | Netflix",
    "channel": "Netflix Latinoamérica",
    "channel_id": "UC5ZiUaIJ2b5dYBYGf5iEUrA",
    "published": "2026-01-22T19:00:00Z",
    "found_at": "2026-01-26T14:16:31.651107",
    "status": "pending",
    "sanitized_name": "El 2026 tiene algo para todos _ ¿Qué sigue_ _ Netflix"
  },
  {
    "video_id": "q06x0oCM7vA",
    "url": "https://www.youtube.com/watch?v=q06x0oCM7vA",
    "title": "Contenido coreano en Netflix para 2026 | ¿Qué sigue? | Netflix",
    "channel": "Netflix Latinoamérica",
    "channel_id": "UC5ZiUaIJ2b5dYBYGf5iEUrA",
    "published": "2026-01-21T00:00:00Z",
    "found_at": "2026-01-26T14:16:31.651110",
    "status": "pending",
    "sanitized_name": "Contenido coreano en Netflix para 2026 _ ¿Qué sigue_ _ Netflix"
  },
  {
    "video_id": "qfrz_1neiSg",
    "url": "https://www.youtube.com/watch?v=qfrz_1neiSg",
    "title": "WWE Greatest Royal Rumble 2026 | Netflix",
    "channel": "Netflix Latinoamérica",
    "channel_id": "UC5ZiUaIJ2b5dYBYGf5iEUrA",
    "published": "2026-01-15T09:00:00Z",
    "found_at": "2026-01-15T13:47:13.557392",
    "status": "metadata_update",
    "sanitized_name": "WWE Greatest Royal Rumble 2026 _ Netflix"
  },
  {
    "video_id": "fhH5VvqAlps",
    "url": "https://www.youtube.com/watch?v=fhH5VvqAlps",
    "title": "Amor de Oficina | Vacante abierta en Sofintim | Netflix",
    "channel": "Netflix Latinoamérica",
    "channel_id": "UC5ZiUaIJ2b5dYBYGf5iEUrA",
    "published": "2026-01-13T16:01:07Z",
    "found_at": "2026-01-13T23:59:01.794349",
    "status": "metadata_update",
    "sanitized_name": "Amor de Oficina _ Vacante abierta en Sofintim _ Netflix"
  },
  {
    "video_id": "eQN2YP0BK4c",
    "url": "https://www.youtube.com/watch?v=eQN2YP0BK4c",
    "title": "Rascacielos en vivo | Tráiler oficial | Netflix",
    "channel": "Netflix Latinoamérica",
    "channel_id": "UC5ZiUaIJ2b5dYBYGf5iEUrA",
    "published": "2026-01-13T14:30:00Z",
    "found_at": "2026-01-13T14:31:34.256405",
    "status": "metadata_update",
    "sanitized_name": "Rascacielos en vivo _ Tráiler oficial _ Netflix"
  },
  {
    "video_id": "Nh7itugdxMc",
    "url": "https://www.youtube.com/watch?v=Nh7itugdxMc",
    "title": "El tour universitario con Joe | Tráiler oficial | Netflix",
    "channel": "Netflix Latinoamérica",
    "channel_id": "UC5ZiUaIJ2b5dYBYGf5iEUrA",
    "published": "2026-01-13T14:00:01Z",
    "found_at": "2026-01-13T14:16:29.158385",
    "status": "pending",
    "sanitized_name": "El tour universitario con Joe _ Tráiler oficial _ Netflix"
  },
  {
    "video_id": "toGUPwdk0tI",
    "url": "https://www.youtube.com/watch?v=toGUPwdk0tI",
    "title": "El arte de Sarah | Avance oficial | Netflix",
    "channel": "Netflix Latinoamérica",
    "channel_id": "UC5ZiUaIJ2b5dYBYGf5iEUrA",
    "published": "2026-01-13T00:00:01Z",
    "found_at": "2026-01-13T13:24:55.341234",
    "status": "uploaded",
    "sanitized_name": "El arte de Sarah _ Avance oficial _ Netflix",
    "metadata_updated_at": "2026-01-13T13:27:12.359865",
    "uploaded_at": "2026-01-13T13:27:18.685140",
    "youtube_id": "jrrBDiYWzBo"
  },
  {
    "video_id": "rF09C9zXnfs",
    "url": "https://www.youtube.com/watch?v=rF09C9zXnfs",
    "title": "ONE PIECE: Temporada 2 | Avance oficial | Netflix",
    "channel": "Netflix Latinoamérica",
    "channel_id": "UC5ZiUaIJ2b5dYBYGf5iEUrA",
    "published": "2026-01-12T15:00:00Z",
    "found_at": "2026-01-13T13:24:55.341248",
    "status": "metadata_update",
    "sanitized_name": "ONE PIECE_ Temporada 2 _ Avance oficial _ Netflix"
  },
  {
    "video_id": "vIttUnWT_fs",
    "url": "https://www.youtube.com/watch?v=vIttUnWT_fs",
    "title": "La carta de despedida para todo el elenco | Stranger Things 5 | Netflix",
    "channel": "Netflix Latinoamérica",
    "channel_id": "UC5ZiUaIJ2b5dYBYGf5iEUrA",
    "published": "2026-01-11T17:00:00Z",
    "found_at": "2026-01-13T13:24:55.341251",
    "status": "metadata_update",
    "sanitized_name": "La carta de despedida para todo el elenco _ Stranger Things 5 _ Netflix"
  },
  {
    "video_id": "BgVpkSfFwHk",
    "url": "https://www.youtube.com/watch?v=BgVpkSfFwHk",
    "title": "Amor de Oficina | Guía para ser el galán de la oficina | Netflix",
    "channel": "Netflix Latinoamérica",
    "channel_id": "UC5ZiUaIJ2b5dYBYGf5iEUrA",
    "published": "2026-01-11T15:00:00Z",
    "found_at": "2026-01-13T13:24:55.341253",
    "status": "metadata_update",
    "sanitized_name": "Amor de Oficina _ Guía para ser el galán de la oficina _ Netflix"
  },
  {
    "video_id": "Hc6oGaYb2yc",
    "url": "https://www.youtube.com/watch?v=Hc6oGaYb2yc",
    "title": "La carta de despedida de Sadie Sink | Stranger Things 5 | Netflix",
    "channel": "Netflix Latinoamérica",
    "channel_id": "UC5ZiUaIJ2b5dYBYGf5iEUrA",
    "published": "2026-01-10T17:00:00Z",
    "found_at": "2026-01-13T13:24:55.341256",
    "status": "metadata_update",
    "sanitized_name": "La carta de despedida de Sadie Sink _ Stranger Things 5 _ Netflix"
  },
  {
    "video_id": "iQ5z4HjD1QE",
    "url": "https://www.youtube.com/watch?v=iQ5z4HjD1QE",
    "title": "Rompiendo el hielo | Tráiler oficial | Netflix",
    "channel": "Netflix Latinoamérica",
    "channel_id": "UC5ZiUaIJ2b5dYBYGf5iEUrA",
    "published": "2026-01-10T03:00:00Z",
    "found_at": "2026-01-10T03:35:08.799247",
    "status": "uploaded",
    "sanitized_name": "Rompiendo el hielo _ Tráiler oficial _ Netflix",
    "metadata_updated_at": "2026-01-10T03:37:26.641849",
    "uploaded_at": "2026-01-10T03:37:31.560769",
    "youtube_id": "2qA-A1qv_1A"
  },
  {
    "video_id": "csaPxc9HkEw",
    "url": "https://www.youtube.com/watch?v=csaPxc9HkEw",
    "title": "La carta de despedida de Finn Wolfhard | Stranger Things 5 | Netflix",
    "channel": "Netflix Latinoamérica",
    "channel_id": "UC5ZiUaIJ2b5dYBYGf5iEUrA",
    "published": "2026-01-09T22:00:47Z",
    "found_at": "2026-01-10T03:35:08.799264",
    "status": "pending",
    "sanitized_name": "La carta de despedida de Finn Wolfhard _ Stranger Things 5 _ Netflix"
  },
  {
    "video_id": "lcuSzPz3SOs",
    "url": "https://www.youtube.com/watch?v=lcuSzPz3SOs",
    "title": "Once: se lanza / Yo desde el sillón: NOOOOO 😭🔥",
    "channel": "Netflix Latinoamérica",
    "channel_id": "UC5ZiUaIJ2b5dYBYGf5iEUrA",
    "published": "2026-01-09T17:30:13Z",
    "found_at": "2026-01-10T03:35:08.799267",
    "status": "pending",
    "sanitized_name": "Once_ se lanza _ Yo desde el sillón_ NOOOOO 😭🔥"
  },
  {
    "video_id": "qkd2z86KXs0",
    "url": "https://www.youtube.com/watch?v=qkd2z86KXs0",
    "title": "La infiltrada Srta. Hong | TRÁILER OFICIAL | Netflix",
    "channel": "Netflix Latinoamérica",
    "channel_id": "UC5ZiUaIJ2b5dYBYGf5iEUrA",
    "published": "2026-01-09T02:00:00Z",
    "found_at": "2026-01-10T03:35:08.799270",
    "status": "uploaded",
    "sanitized_name": "La infiltrada Srta. Hong _ TRÁILER OFICIAL _ Netflix",
    "metadata_updated_at": "2026-01-10T05:51:52.391182",
    "uploaded_at": "2026-01-10T05:51:58.747892",
    "youtube_id": "Jq5IP2JTKzk"
  },
  {
    "video_id": "Hxn2dD3ggck",
    "url": "https://www.youtube.com/watch?v=Hxn2dD3ggck",
    "title": "El discurso de graduación de Dustin | Stranger Things 5 ​​| Netflix",
    "channel": "Netflix Latinoamérica",
    "channel_id": "UC5ZiUaIJ2b5dYBYGf5iEUrA",
    "published": "2026-01-08T22:00:28Z",
    "found_at": "2026-01-10T03:35:08.799272",
    "status": "pending",
    "sanitized_name": "El discurso de graduación de Dustin _ Stranger Things 5 ​​_ Netflix"
  },
  {
    "video_id": "2F-j-jdMBEQ",
    "url": "https://www.youtube.com/watch?v=2F-j-jdMBEQ",
    "title": "La carta de despedida de Noah Schnapp | Stranger Things 5 | Netflix",
    "channel": "Netflix Latinoamérica",
    "channel_id": "UC5ZiUaIJ2b5dYBYGf5iEUrA",
    "published": "2026-01-08T20:00:06Z",
    "found_at": "2026-01-10T03:35:08.799274",
    "status": "pending",
    "sanitized_name": "La carta de despedida de Noah Schnapp _ Stranger Things 5 _ Netflix"
  },
  {
    "video_id": "Bl-pKLCQy6s",
    "url": "https://www.youtube.com/watch?v=Bl-pKLCQy6s",
    "title": "El Caballero de los Siete Reinos | En los próximos episodios | HBO Max",
    "channel": "HBO Max Latinoamérica",
    "channel_id": "UCjq5m8s71qA9ZMfJw0q7Fgw",
    "published": "2026-01-27T00:00:11Z",
    "found_at": "2026-01-27T03:02:55.394523",
    "status": "metadata_update",
    "sanitized_name": "El Caballero de los Siete Reinos _ En los próximos episodios _ HBO Max"
  },
  {
    "video_id": "YYyWOWnmjdU",
    "url": "https://www.youtube.com/watch?v=YYyWOWnmjdU",
    "title": "Podcast: El Caballero de los Siete Reinos | Episodio 2 | HBO Max",
    "channel": "HBO Max Latinoamérica",
    "channel_id": "UCjq5m8s71qA9ZMfJw0q7Fgw",
    "published": "2026-01-26T19:00:28Z",
    "found_at": "2026-01-27T03:02:55.394538",
    "status": "metadata_update",
    "sanitized_name": "Podcast_ El Caballero de los Siete Reinos _ Episodio 2 _ HBO Max"
  },
  {
    "video_id": "zDU61or2Fkc",
    "url": "https://www.youtube.com/watch?v=zDU61or2Fkc",
    "title": "Podcast: El Caballero de los Siete Reinos | Episodio 1 | HBO Max",
    "channel": "HBO Max Latinoamérica",
    "channel_id": "UCjq5m8s71qA9ZMfJw0q7Fgw",
    "published": "2026-01-26T16:52:09Z",
    "found_at": "2026-01-27T03:02:55.394541",
    "status": "metadata_update",
    "sanitized_name": "Podcast_ El Caballero de los Siete Reinos _ Episodio 1 _ HBO Max"
  },
  {
    "video_id": "eyOi9eKyo7I",
    "url": "https://www.youtube.com/watch?v=eyOi9eKyo7I",
    "title": "El mejor escudero de Westeros 😎 #ElCaballerodelosSieteReinos #GOT #Egg #AKnightoftheSevenKingdoms",
    "channel": "HBO Max Latinoamérica",
    "channel_id": "UCjq5m8s71qA9ZMfJw0q7Fgw",
    "published": "2026-01-26T03:01:46Z",
    "found_at": "2026-01-26T14:16:31.929385",
    "status": "pending",
    "sanitized_name": "El mejor escudero de Westeros 😎 #ElCaballerodelosSieteReinos #GOT #Egg #AKnightoftheSevenKingdoms"
  },
  {
    "video_id": "Qn9D7BGCL1Q",
    "url": "https://www.youtube.com/watch?v=Qn9D7BGCL1Q",
    "title": "No contaban con mi astucia (ni con mi estrés) #LosColorado, ya disponible en HBO Max",
    "channel": "HBO Max Latinoamérica",
    "channel_id": "UCjq5m8s71qA9ZMfJw0q7Fgw",
    "published": "2026-01-24T20:00:15Z",
    "found_at": "2026-01-26T14:16:31.929401",
    "status": "pending",
    "sanitized_name": "No contaban con mi astucia (ni con mi estrés) #LosColorado, ya disponible en HBO Max"
  },
  {
    "video_id": "Ed9HPIpUiR4",
    "url": "https://www.youtube.com/watch?v=Ed9HPIpUiR4",
    "title": "Te queremos mucho, Dunk ❤️ #ElCaballerodelosSieteReinos",
    "channel": "HBO Max Latinoamérica",
    "channel_id": "UCjq5m8s71qA9ZMfJw0q7Fgw",
    "published": "2026-01-24T16:00:18Z",
    "found_at": "2026-01-26T14:16:31.929405",
    "status": "pending",
    "sanitized_name": "Te queremos mucho, Dunk ❤️ #ElCaballerodelosSieteReinos"
  },
  {
    "video_id": "rO3ZDgrWfUg",
    "url": "https://www.youtube.com/watch?v=rO3ZDgrWfUg",
    "title": "Yo tampoco querría enfrentarme a Pennywise en un juicio por combate. 😅 🎈#ElCaballeroDeLosSieteReinos",
    "channel": "HBO Max Latinoamérica",
    "channel_id": "UCjq5m8s71qA9ZMfJw0q7Fgw",
    "published": "2026-01-23T21:00:56Z",
    "found_at": "2026-01-26T14:16:31.929408",
    "status": "pending",
    "sanitized_name": "Yo tampoco querría enfrentarme a Pennywise en un juicio por combate. 😅 🎈#ElCaballeroDeLosSieteReinos"
  },
  {
    "video_id": "cPziPAfPmxY",
    "url": "https://www.youtube.com/watch?v=cPziPAfPmxY",
    "title": "El Chapulín Colorado y su familia vuelven en la T2 de #LosColorado. ❤️💛",
    "channel": "HBO Max Latinoamérica",
    "channel_id": "UCjq5m8s71qA9ZMfJw0q7Fgw",
    "published": "2026-01-23T20:19:03Z",
    "found_at": "2026-01-26T14:16:31.929411",
    "status": "pending",
    "sanitized_name": "El Chapulín Colorado y su familia vuelven en la T2 de #LosColorado. ❤️💛"
  },
  {
    "video_id": "V6nu4lGvRnQ",
    "url": "https://www.youtube.com/watch?v=V6nu4lGvRnQ",
    "title": "Los que tenemos dos pies izquierdos nos identificamos con esta escena 😅 #ElCaballeroDeLosSieteReinos",
    "channel": "HBO Max Latinoamérica",
    "channel_id": "UCjq5m8s71qA9ZMfJw0q7Fgw",
    "published": "2026-01-23T15:36:45Z",
    "found_at": "2026-01-26T14:16:31.929414",
    "status": "pending",
    "sanitized_name": "Los que tenemos dos pies izquierdos nos identificamos con esta escena 😅 #ElCaballeroDeLosSieteReinos"
  },
  {
    "video_id": "oN4eWeluDxw",
    "url": "https://www.youtube.com/watch?v=oN4eWeluDxw",
    "title": "La historia hasta ahora | Margarita - Temporada 2 🌼 | HBO Max",
    "channel": "HBO Max Latinoamérica",
    "channel_id": "UCjq5m8s71qA9ZMfJw0q7Fgw",
    "published": "2026-01-22T21:00:59Z",
    "found_at": "2026-01-26T14:16:31.929416",
    "status": "pending",
    "sanitized_name": "La historia hasta ahora _ Margarita - Temporada 2 🌼 _ HBO Max"
  },
  {
    "video_id": "Fy6nIOn_pdM",
    "url": "https://www.youtube.com/watch?v=Fy6nIOn_pdM",
    "title": "Como Agua Para Chocolate - Temporada Final | Tráiler Oficial | HBO Max",
    "channel": "HBO Max Latinoamérica",
    "channel_id": "UCjq5m8s71qA9ZMfJw0q7Fgw",
    "published": "2026-01-22T16:00:14Z",
    "found_at": "2026-01-26T14:16:31.929419",
    "status": "pending",
    "sanitized_name": "Como Agua Para Chocolate - Temporada Final _ Tráiler Oficial _ HBO Max"
  },
  {
    "video_id": "NI1xF0HvsbU",
    "url": "https://www.youtube.com/watch?v=NI1xF0HvsbU",
    "title": "The Pitt - Temporada 2 | Promo oficial Episodio 3 | HBO Max",
    "channel": "HBO Max Latinoamérica",
    "channel_id": "UCjq5m8s71qA9ZMfJw0q7Fgw",
    "published": "2026-01-22T13:58:33Z",
    "found_at": "2026-01-26T14:16:31.929421",
    "status": "pending",
    "sanitized_name": "The Pitt - Temporada 2 _ Promo oficial Episodio 3 _ HBO Max"
  },
  {
    "video_id": "puHK7N55kYw",
    "url": "https://www.youtube.com/watch?v=puHK7N55kYw",
    "title": "Había una vez | Margarita | HBO Max",
    "channel": "HBO Max Latinoamérica",
    "channel_id": "UCjq5m8s71qA9ZMfJw0q7Fgw",
    "published": "2026-01-20T22:01:05Z",
    "found_at": "2026-01-26T14:16:31.929424",
    "status": "pending",
    "sanitized_name": "Había una vez _ Margarita _ HBO Max"
  },
  {
    "video_id": "Y2HBcDvPdKQ",
    "url": "https://www.youtube.com/watch?v=Y2HBcDvPdKQ",
    "title": "Cuando sea grande quiero ser como la abuela Colorado 👵🏼 #LosColorado ya disponible en HBO Max",
    "channel": "HBO Max Latinoamérica",
    "channel_id": "UCjq5m8s71qA9ZMfJw0q7Fgw",
    "published": "2026-01-14T23:12:23Z",
    "found_at": "2026-01-15T00:09:47.470963",
    "status": "pending",
    "sanitized_name": "Cuando sea grande quiero ser como la abuela Colorado 👵🏼 #LosColorado ya disponible en HBO Max"
  },
  {
    "video_id": "HOj6B2HYZl4",
    "url": "https://www.youtube.com/watch?v=HOj6B2HYZl4",
    "title": "Gracias Dra. Garcia por confirmarlo ↔️ #ThePitt Temporada 2 nuevo episodio cada jueves, por HBOMax",
    "channel": "HBO Max Latinoamérica",
    "channel_id": "UCjq5m8s71qA9ZMfJw0q7Fgw",
    "published": "2026-01-14T20:00:15Z",
    "found_at": "2026-01-15T00:09:47.470980",
    "status": "pending",
    "sanitized_name": "Gracias Dra. Garcia por confirmarlo ↔️ #ThePitt Temporada 2 nuevo episodio cada jueves, por HBOMax"
  },
  {
    "video_id": "RaivNOscDXE",
    "url": "https://www.youtube.com/watch?v=RaivNOscDXE",
    "title": "Euphoria - 3 Temporada | Tráiler Oficial | HBO Max",
    "channel": "HBO Max Latinoamérica",
    "channel_id": "UCjq5m8s71qA9ZMfJw0q7Fgw",
    "published": "2026-01-14T16:06:21Z",
    "found_at": "2026-01-15T00:09:47.470984",
    "status": "pending",
    "sanitized_name": "Euphoria - 3 Temporada _ Tráiler Oficial _ HBO Max"
  },
  {
    "video_id": "bruJZruT0LY",
    "url": "https://www.youtube.com/watch?v=bruJZruT0LY",
    "title": "Cuando el alumno repite el gesto, el maestro no necesita decir nada ❤️‍🩹 #ThePitt T2 ya, por HBOMax",
    "channel": "HBO Max Latinoamérica",
    "channel_id": "UCjq5m8s71qA9ZMfJw0q7Fgw",
    "published": "2026-01-09T01:00:52Z",
    "found_at": "2026-01-10T03:35:09.048565",
    "status": "pending",
    "sanitized_name": "Cuando el alumno repite el gesto, el maestro no necesita decir nada ❤️‍🩹 #ThePitt T2 ya, por HBOMax"
  },
  {
    "video_id": "Ak9ICucMIHU",
    "url": "https://www.youtube.com/watch?v=Ak9ICucMIHU",
    "title": "Como Agua Para Chocolate - Temporada final | Teaser Oficial | HBO Max",
    "channel": "HBO Max Latinoamérica",
    "channel_id": "UCjq5m8s71qA9ZMfJw0q7Fgw",
    "published": "2026-01-08T16:00:35Z",
    "found_at": "2026-01-08T16:30:34.201998",
    "status": "pending",
    "sanitized_name": "Como Agua Para Chocolate - Temporada final _ Teaser Oficial _ HBO Max"
  },
  {
    "video_id": "-4Fxfz9d2HQ",
    "url": "https://www.youtube.com/watch?v=-4Fxfz9d2HQ",
    "title": "Alguien que abrace al Dr. Robby ❤️‍🩹 #ThePitt temporada 2, el 8 de enero por HBO Max.",
    "channel": "HBO Max Latinoamérica",
    "channel_id": "UCjq5m8s71qA9ZMfJw0q7Fgw",
    "published": "2026-01-07T16:05:13Z",
    "found_at": "2026-01-08T15:59:40.535491",
    "status": "metadata_update",
    "sanitized_name": "Alguien que abrace al Dr. Robby ❤️‍🩹 #ThePitt temporada 2, el 8 de enero por HBO Max."
  },
  {
    "video_id": "7-lB6hPZOjw",
    "url": "https://www.youtube.com/watch?v=7-lB6hPZOjw",
    "title": "Primal | Tráiler Oficial | HBO Max",
    "channel": "HBO Max Latinoamérica",
    "channel_id": "UCjq5m8s71qA9ZMfJw0q7Fgw",
    "published": "2026-01-06T13:00:14Z",
    "found_at": "2026-01-06T13:42:58.789290",
    "status": "metadata_update",
    "sanitized_name": "Primal _ Tráiler Oficial _ HBO Max"
  },
  {
    "video_id": "TOzkqkuD62Q",
    "url": "https://www.youtube.com/watch?v=TOzkqkuD62Q",
    "title": "¿Reconoces quién está detrás de la Servoarmadura? Te leemos 👀#Shorts #Fallout #Servoarmadura",
    "channel": "Prime Video Latinoamérica",
    "channel_id": "UCP7i-E6AYr-UChpNcO0EEag",
    "published": "2026-01-26T21:00:33Z",
    "found_at": "2026-01-27T03:02:55.719042",
    "status": "metadata_update",
    "sanitized_name": "¿Reconoces quién está detrás de la Servoarmadura_ Te leemos 👀#Shorts #Fallout #Servoarmadura"
  },
  {
    "video_id": "1wx3XvFbyVc",
    "url": "https://www.youtube.com/watch?v=1wx3XvFbyVc",
    "title": "Las batallas de Luffy siempre son las MÁS SALVAJES. #OnePieceFilmRed #shorts",
    "channel": "Prime Video Latinoamérica",
    "channel_id": "UCP7i-E6AYr-UChpNcO0EEag",
    "published": "2026-01-26T17:00:31Z",
    "found_at": "2026-01-27T03:02:55.719057",
    "status": "metadata_update",
    "sanitized_name": "Las batallas de Luffy siempre son las MÁS SALVAJES. #OnePieceFilmRed #shorts"
  },
  {
    "video_id": "Cd_6hlVT6a0",
    "url": "https://www.youtube.com/watch?v=Cd_6hlVT6a0",
    "title": "FRAN FINE INVENTÓ EL ASMR Y LA VOZ NASAL, TODO EN LA MISMA ESCENA 😌💆 #TheNanny #MíraloEnPrimeVideo",
    "channel": "Prime Video Latinoamérica",
    "channel_id": "UCP7i-E6AYr-UChpNcO0EEag",
    "published": "2026-01-25T21:00:54Z",
    "found_at": "2026-01-26T14:16:32.138248",
    "status": "pending",
    "sanitized_name": "FRAN FINE INVENTÓ EL ASMR Y LA VOZ NASAL, TODO EN LA MISMA ESCENA 😌💆 #TheNanny #MíraloEnPrimeVideo"
  },
  {
    "video_id": "6nM6Zl6K_3U",
    "url": "https://www.youtube.com/watch?v=6nM6Zl6K_3U",
    "title": "¿QUÉ ES LO MÁS RARO QUE HAS HECHO POR AMOR? #LeccionesDeUnPingüino #Shorts",
    "channel": "Prime Video Latinoamérica",
    "channel_id": "UCP7i-E6AYr-UChpNcO0EEag",
    "published": "2026-01-25T16:00:51Z",
    "found_at": "2026-01-26T14:16:32.138264",
    "status": "pending",
    "sanitized_name": "¿QUÉ ES LO MÁS RARO QUE HAS HECHO POR AMOR_ #LeccionesDeUnPingüino #Shorts"
  },
  {
    "video_id": "YPlkX-tMY2k",
    "url": "https://www.youtube.com/watch?v=YPlkX-tMY2k",
    "title": "Esos sueños están bien okie dokie #Fallout #shorts",
    "channel": "Prime Video Latinoamérica",
    "channel_id": "UCP7i-E6AYr-UChpNcO0EEag",
    "published": "2026-01-24T21:00:46Z",
    "found_at": "2026-01-26T14:16:32.138267",
    "status": "pending",
    "sanitized_name": "Esos sueños están bien okie dokie #Fallout #shorts"
  },
  {
    "video_id": "Oy8o8FMO270",
    "url": "https://www.youtube.com/watch?v=Oy8o8FMO270",
    "title": "Si tan solo mi jefe entendiera mis indirectas #YoSoyBettyLaFea #shorts",
    "channel": "Prime Video Latinoamérica",
    "channel_id": "UCP7i-E6AYr-UChpNcO0EEag",
    "published": "2026-01-24T16:00:45Z",
    "found_at": "2026-01-26T14:16:32.138270",
    "status": "pending",
    "sanitized_name": "Si tan solo mi jefe entendiera mis indirectas #YoSoyBettyLaFea #shorts"
  },
  {
    "video_id": "UxBUwgsSW5k",
    "url": "https://www.youtube.com/watch?v=UxBUwgsSW5k",
    "title": "¿Se dieron cuenta de quién es el súper mutante? 🤫 #Fallout",
    "channel": "Prime Video Latinoamérica",
    "channel_id": "UCP7i-E6AYr-UChpNcO0EEag",
    "published": "2026-01-23T21:00:21Z",
    "found_at": "2026-01-26T14:16:32.138273",
    "status": "pending",
    "sanitized_name": "¿Se dieron cuenta de quién es el súper mutante_ 🤫 #Fallout"
  },
  {
    "video_id": "fwfVcaLOgQs",
    "url": "https://www.youtube.com/watch?v=fwfVcaLOgQs",
    "title": "Nos pedimos uno, es para una tarea 👀 #RomperElCírculo #Shorts",
    "channel": "Prime Video Latinoamérica",
    "channel_id": "UCP7i-E6AYr-UChpNcO0EEag",
    "published": "2026-01-23T16:01:18Z",
    "found_at": "2026-01-26T14:16:32.138276",
    "status": "pending",
    "sanitized_name": "Nos pedimos uno, es para una tarea 👀 #RomperElCírculo #Shorts"
  },
  {
    "video_id": "NYD5GB2Qvpo",
    "url": "https://www.youtube.com/watch?v=NYD5GB2Qvpo",
    "title": "LOVE ME LOVE ME | Tráiler Oficial | Prime Video",
    "channel": "Prime Video Latinoamérica",
    "channel_id": "UCP7i-E6AYr-UChpNcO0EEag",
    "published": "2026-01-23T14:00:00Z",
    "found_at": "2026-01-26T14:16:32.138279",
    "status": "pending",
    "sanitized_name": "LOVE ME LOVE ME _ Tráiler Oficial _ Prime Video"
  },
  {
    "video_id": "gHkbRDBdTGU",
    "url": "https://www.youtube.com/watch?v=gHkbRDBdTGU",
    "title": "Qué decisión tan difícil, por suerte no la tengo que tomar yo. 😂 #BeastGames",
    "channel": "Prime Video Latinoamérica",
    "channel_id": "UCP7i-E6AYr-UChpNcO0EEag",
    "published": "2026-01-22T22:00:52Z",
    "found_at": "2026-01-27T03:02:55.719062",
    "status": "metadata_update",
    "sanitized_name": "Qué decisión tan difícil, por suerte no la tengo que tomar yo. 😂 #BeastGames"
  },
  {
    "video_id": "_O-aUHNIteE",
    "url": "https://www.youtube.com/watch?v=_O-aUHNIteE",
    "title": "Invencible Temporada 4 – Trailer Oficial | Prime Video",
    "channel": "Prime Video Latinoamérica",
    "channel_id": "UCP7i-E6AYr-UChpNcO0EEag",
    "published": "2026-01-22T17:00:00Z",
    "found_at": "2026-01-27T03:02:55.719065",
    "status": "metadata_update",
    "sanitized_name": "Invencible Temporada 4 – Trailer Oficial _ Prime Video"
  },
  {
    "video_id": "r_c8cbbA0jU",
    "url": "https://www.youtube.com/watch?v=r_c8cbbA0jU",
    "title": "Dr. House salvando el día una vez más 😮‍💨 #House #shorts",
    "channel": "Prime Video Latinoamérica",
    "channel_id": "UCP7i-E6AYr-UChpNcO0EEag",
    "published": "2026-01-21T21:00:17Z",
    "found_at": "2026-01-26T14:16:32.138281",
    "status": "pending",
    "sanitized_name": "Dr. House salvando el día una vez más 😮‍💨 #House #shorts"
  },
  {
    "video_id": "LrZCm09A_oM",
    "url": "https://www.youtube.com/watch?v=LrZCm09A_oM",
    "title": "56 Días - Trailer Oficial | Prime Video",
    "channel": "Prime Video Latinoamérica",
    "channel_id": "UCP7i-E6AYr-UChpNcO0EEag",
    "published": "2026-01-21T15:29:50Z",
    "found_at": "2026-01-26T14:16:32.138284",
    "status": "pending",
    "sanitized_name": "56 Días - Trailer Oficial _ Prime Video"
  },
  {
    "video_id": "yoWZ87qsxgc",
    "url": "https://www.youtube.com/watch?v=yoWZ87qsxgc",
    "title": "Sí somos 🫣​ #Ted2 #short",
    "channel": "Prime Video Latinoamérica",
    "channel_id": "UCP7i-E6AYr-UChpNcO0EEag",
    "published": "2026-01-14T21:01:55Z",
    "found_at": "2026-01-15T00:09:47.778563",
    "status": "pending",
    "sanitized_name": "Sí somos 🫣​ #Ted2 #short"
  },
  {
    "video_id": "7B_vsPz8GcA",
    "url": "https://www.youtube.com/watch?v=7B_vsPz8GcA",
    "title": "El Engaño - Tráiler Oficial I Prime Video",
    "channel": "Prime Video Latinoamérica",
    "channel_id": "UCP7i-E6AYr-UChpNcO0EEag",
    "published": "2026-01-14T15:01:42Z",
    "found_at": "2026-01-15T00:09:47.778579",
    "status": "pending",
    "sanitized_name": "El Engaño - Tráiler Oficial I Prime Video"
  },
  {
    "video_id": "LcXGPgh_MdI",
    "url": "https://www.youtube.com/watch?v=LcXGPgh_MdI",
    "title": "Cómo no decir que es el mejor doctor  ​ #TheGoodDoctor #short",
    "channel": "Prime Video Latinoamérica",
    "channel_id": "UCP7i-E6AYr-UChpNcO0EEag",
    "published": "2026-01-13T21:34:21Z",
    "found_at": "2026-01-13T23:59:02.310135",
    "status": "metadata_update",
    "sanitized_name": "Cómo no decir que es el mejor doctor  ​ #TheGoodDoctor #short"
  },
  {
    "video_id": "qnvg87mbt_A",
    "url": "https://www.youtube.com/watch?v=qnvg87mbt_A",
    "title": "Lo que llega en enero 2026",
    "channel": "Prime Video Latinoamérica",
    "channel_id": "UCP7i-E6AYr-UChpNcO0EEag",
    "published": "2026-01-13T20:30:21Z",
    "found_at": "2026-01-13T23:59:02.310167",
    "status": "metadata_update",
    "sanitized_name": "Lo que llega en enero 2026"
  },
  {
    "video_id": "QGaLrqSFRFA",
    "url": "https://www.youtube.com/watch?v=QGaLrqSFRFA",
    "title": "Más que la prima parece la hija. #TheNanny",
    "channel": "Prime Video Latinoamérica",
    "channel_id": "UCP7i-E6AYr-UChpNcO0EEag",
    "published": "2026-01-13T16:00:31Z",
    "found_at": "2026-01-13T23:59:02.310170",
    "status": "metadata_update",
    "sanitized_name": "Más que la prima parece la hija. #TheNanny"
  },
  {
    "video_id": "9lJQjTysep4",
    "url": "https://www.youtube.com/watch?v=9lJQjTysep4",
    "title": "De niño no eliges tu familia…​ ¿Team Ryan o Team Homelander?​ #TheBoys #Homelander​ #Shorts",
    "channel": "Prime Video Latinoamérica",
    "channel_id": "UCP7i-E6AYr-UChpNcO0EEag",
    "published": "2026-01-12T21:01:14Z",
    "found_at": "2026-01-13T13:24:55.844155",
    "status": "metadata_update",
    "sanitized_name": "De niño no eliges tu familia…​ ¿Team Ryan o Team Homelander_​ #TheBoys #Homelander​ #Shorts"
  },
  {
    "video_id": "oaPc6aN8d08",
    "url": "https://www.youtube.com/watch?v=oaPc6aN8d08",
    "title": "No diré quién soy... 😳 #TheOffice #Shorts",
    "channel": "Prime Video Latinoamérica",
    "channel_id": "UCP7i-E6AYr-UChpNcO0EEag",
    "published": "2026-01-12T17:00:18Z",
    "found_at": "2026-01-13T13:24:55.844170",
    "status": "metadata_update",
    "sanitized_name": "No diré quién soy... 😳 #TheOffice #Shorts"
  }
]